{
	"configurations" : 
	[
		{
			"directories" : 
			[
				{
					"build" : ".",
					"jsonFile" : "directory-.-Debug-d0094a50bb2071803777.json",
					"projectIndex" : 0,
					"source" : ".",
					"targetIndexes" : 
					[
						0,
						1
					]
				}
			],
			"name" : "Debug",
			"projects" : 
			[
				{
					"directoryIndexes" : 
					[
						0
					],
					"name" : "Project",
					"targetIndexes" : 
					[
						0,
						1
					]
				}
			],
			"targets" : 
			[
				{
					"directoryIndex" : 0,
					"id" : "0000_basic_exam01::@6890427a1f51a3e7e1df",
					"jsonFile" : "target-0000_basic_exam01-Debug-d1aae1971b4dbc6c045d.json",
					"name" : "0000_basic_exam01",
					"projectIndex" : 0
				},
				{
					"directoryIndex" : 0,
					"id" : "0001_BOJ_05_BFS_2178_BOJ::@6890427a1f51a3e7e1df",
					"jsonFile" : "target-0001_BOJ_05_BFS_2178_BOJ-Debug-a2ac80b418132ae4eb04.json",
					"name" : "0001_BOJ_05_BFS_2178_BOJ",
					"projectIndex" : 0
				}
			]
		}
	],
	"kind" : "codemodel",
	"paths" : 
	{
		"build" : "C:/Users/user/CLionProjects/CplusAlgorithm/cmake-build-debug",
		"source" : "C:/Users/user/CLionProjects/CplusAlgorithm"
	},
	"version" : 
	{
		"major" : 2,
		"minor" : 6
	}
}
